rtl/axi_fifo.sv

module axi_fifo 
#(
    parameter WIDTH=64, 
    parameter DEPTH=5,
    parameter PTR_WIDTH = $clog2(DEPTH)
    )
(
    input                           clk,
    input                           rst_n,
    input                           rdy_out,
    input                           vld_in,
    input        [WIDTH-1:0]        data_in,
    output logic [WIDTH-1:0]        data_out,
    output logic                    rdy_in,
    output logic                    vld_out
);

parameter COUNT_WIDTH = ($clog2(DEPTH)-1 > 3) ? $clog2(DEPTH)-1 : 3;

logic [WIDTH-1:0]      buffer [0:DEPTH-1];
logic [PTR_WIDTH:0]  write_ptr;
logic [PTR_WIDTH:0]  read_ptr;

logic [COUNT_WIDTH:0]  count;

initial begin
    write_ptr    = '0;
    read_ptr     = '0;
    count        = '0;
    data_out     = buffer[0];

    // Display error if WIDTH is 0 or less.
    if (WIDTH <= 0) begin
        $error("%m ** Illegal condition **, you used %d WIDTH", WIDTH);
    end
    // Display error if DEPTH is 0 or less.
    if (DEPTH <= 0) begin
        $error("%m ** Illegal condition **, you used %d DEPTH", DEPTH);
    end

end // end initial


always_comb begin
    vld_out        = !(count == 0);
    rdy_in         =  (count < DEPTH);
end

logic [PTR_WIDTH:0] next_read_ptr;

always_ff @(posedge clk) begin
    if (!rst_n) begin
        write_ptr    <= '0;
        read_ptr     <= '0;
        count        <= '0;
        data_out     <= buffer[0];
    end else begin 
        if (vld_in && rdy_in) begin
            buffer[write_ptr[PTR_WIDTH-1:0]] <= data_in;
            if (count == 0) begin
                data_out <= data_in;
            end
            write_ptr                        <= next_ptr_index(write_ptr);
        end
        if (vld_out && rdy_out) begin
            next_read_ptr = next_ptr_index(read_ptr);
            data_out  <= buffer[next_read_ptr[PTR_WIDTH-1:0]];
            read_ptr  <= next_read_ptr;
        end
        if (vld_in && rdy_in && vld_out && rdy_out) begin
            count <= count; 
        end else if (vld_in && rdy_in) begin
            count <= count + 1; 
        end else if (vld_out && rdy_out) begin
            count <= count - 1;
        end
    end
end

function [PTR_WIDTH:0] next_ptr_index(
    input [PTR_WIDTH:0] ptr
);

if (ptr >= (DEPTH-1)) begin
    return 0;
end else begin
    return ptr + 1;
end

endfunction


endmodule

tests/tb_axi_fifo/tb_axi_fifo.sv
`timescale 1ns/1ps

module tb_axi_fifo;

// Clock & reset
logic clk;
logic rst_n;

// Probe signals for three FIFOs: default, small, medium
// FIFO #1: default parameters (WIDTH=64, DEPTH=5)
logic                   rdy_out1, vld_in1;
logic [63:0]            data_in1;
logic [63:0]            data_out1;
logic                   rdy_in1,  vld_out1;

// FIFO #2: WIDTH=8, DEPTH=4
logic                   rdy_out2, vld_in2;
logic [7:0]             data_in2;
logic [7:0]             data_out2;
logic                   rdy_in2,  vld_out2;

// FIFO #3: WIDTH=16, DEPTH=8
logic                   rdy_out3, vld_in3;
logic [15:0]            data_in3;
logic [15:0]            data_out3;
logic                   rdy_in3,  vld_out3;

// Clock generator
localparam PERIOD = 10;
initial begin
clk = 0;
forever #(PERIOD/2) clk = ~clk;
end

// Necessary to create Waveform
initial begin
// Name as needed
$dumpfile("tb_axi_fifo.vcd");
$dumpvars(0);
end

// Instantiate FIFO #1: default parameters
axi_fifo #(.WIDTH(64), .MIN_DEPTH(16)) fifo1 (
.clk      (clk),
.rst_n    (rst_n),
.rdy_out  (rdy_out1),
.vld_in   (vld_in1),
.data_in  (data_in1),
.data_out (data_out1),
.rdy_in   (rdy_in1),
.vld_out  (vld_out1)
);

// Instantiate FIFO #2: WIDTH=8, DEPTH=4
axi_fifo #( .WIDTH(8), .MIN_DEPTH(4) ) fifo2 (
.clk      (clk),
.rst_n    (rst_n),
.rdy_out  (rdy_out2),
.vld_in   (vld_in2),
.data_in  (data_in2),
.data_out (data_out2),
.rdy_in   (rdy_in2),
.vld_out  (vld_out2)
);

// Instantiate FIFO #3: WIDTH=16, DEPTH=8
axi_fifo #( .WIDTH(16), .MIN_DEPTH(8) ) fifo3 (
.clk      (clk),
.rst_n    (rst_n),
.rdy_out  (rdy_out3),
.vld_in   (vld_in3),
.data_in  (data_in3),
.data_out (data_out3),
.rdy_in   (rdy_in3),
.vld_out  (vld_out3)
);

logic [63:0] fifo_64 [$];
logic [15:0] fifo_16 [$];
logic [7:0]  fifo_8  [$];

logic [63:0] count_64;
logic [63:0] count_16;
logic [63:0] count_8;

initial begin
    count_64 = 0;
    count_16 = 0;
    count_8 = 0;
end

 

  // Task: enqueue N words into a given FIFO instance
  task automatic push_words;
    input  int          id;
    input  int          n;
    begin
        logic  [63:0] big_rand;
        logic  [7:0]  small_rand;
        logic  [15:0] med_rand;
        logic  [31:0] temp;
        int i;
        for (i=0; i<n; i++) begin
        case (id)
          1: begin
                // generate a pattern for FIFO1
                wait (rdy_in1); // ensure ready
                big_rand = {$urandom, $urandom};
                fifo_64.push_back(big_rand);
                @(negedge clk);
                data_in1 = fifo_64[$];
                vld_in1  = 1;
                @(negedge clk);
                vld_in1  = 0;
             end

          2: begin
                wait (rdy_in2);
                temp = $urandom;
                small_rand = temp[7:0];
                fifo_8.push_back(small_rand);
                @(negedge clk);
                data_in2 = fifo_8[$];
                vld_in2  = 1;
                @(negedge clk);
                vld_in2  = 0;
             end

          3: begin
                wait (rdy_in3);
                temp = $urandom;
                med_rand = temp[15:0];
                fifo_16.push_back(med_rand);
                @(negedge clk);
                data_in3 = fifo_16[$];
                vld_in3  = 1;
                @(negedge clk);
                vld_in3  = 0;
             end
        endcase
      end
    end
  endtask

  // Task: dequeue N words from a given FIFO instance and check correctness
  task automatic pop_and_check;
    input  int          id;
    input  int          n;
    begin

        int i;
        for (i=0; i<n; i++) begin
        case (id)
          1: begin
                // check valid and data
                assert (vld_out1) else $error("FIFO1 underflow on pop #%0d", i);
                assert (data_out1 == fifo_64[count_64])
                    else $error("FIFO1 data mismatch: got %h, expected %h", data_out1, fifo_64[count_64]);
                count_64 += 1;
                @(negedge clk);
                rdy_out1 = 1;
                @(negedge clk);
                rdy_out1 = 0;
             end

          2: begin
                // check valid and data
                assert (vld_out2) else $error("FIFO2 underflow on pop #%0d", i);
                assert (data_out2 == fifo_8[count_8])
                    else $error("FIFO2 data mismatch: got %h, expected %h", data_out2, fifo_8[count_8]);
                count_8 += 1;
                @(negedge clk);
                rdy_out2 = 1;
                @(negedge clk);
                rdy_out2 = 0;
             end

          3: begin
                // check valid and data
                assert (vld_out3) else $error("FIFO3 underflow on pop #%0d", i);
                assert (data_out3 == fifo_16[count_16])
                    else $error("FIFO3 data mismatch: got %h, expected %h", data_out3, fifo_16[count_16]);
                count_16 += 1;
                @(negedge clk);
                rdy_out3 = 1;
                @(negedge clk);
                rdy_out3 = 0;
             end
        endcase
      end
    end
  endtask



  // Main test sequence
  initial begin

    // Wait for reset deassertion
    rst_n = 0;
    @(negedge clk);
    rst_n = 1;
    @(negedge clk);

    // Test 1: Fill then drain each FIFO fully
    push_words(1, 16);     // FIFO1 depth=16
    pop_and_check(1, 16);

    push_words(2, 4);     // FIFO2 depth=4
    pop_and_check(2, 4);

    push_words(3, 8);     // FIFO3 depth=8
    pop_and_check(3, 8);

    // Test 2: Push/Pop interleaved, random counts
    push_words(1, 3);
    pop_and_check(1, 2);
    push_words(1, 4);
    pop_and_check(1, 5);

    // Test 3: Full/Empty flag checks
    // Attempt to overfill
    push_words(2, 4);
    @(negedge clk);
    vld_in2 = 1; data_in2 = 8'hFF;
    @(negedge clk);
    vld_in2 = 0;
    assert (!rdy_in2) else $error("FIFO2 allowed write when full");
    pop_and_check(2, 4);

    // Attempt to over-empty
    @(negedge clk);
    rdy_out3 = 1;
    @(negedge clk);
    rdy_out3 = 0;
    assert (!vld_out3) else $error("FIFO3 asserted valid when empty");

    $display("All tests passed.");
    $finish;
  end

endmodule

tests/tb_axi_fifo/tb_axi_fifo.vcd
$version Generated by VerilatedVcd $end
$timescale 1ps $end
 $scope module $rootio $end
 $upscope $end
 $scope module tb_axi_fifo $end
  $var wire 1 ` clk $end
  $var wire 1 # rst_n $end
  $var wire 1 $ rdy_out1 $end
  $var wire 1 % vld_in1 $end
  $var wire 64 & data_in1 [63:0] $end
  $var wire 64 4 data_out1 [63:0] $end
  $var wire 1 6 rdy_in1 $end
  $var wire 1 7 vld_out1 $end
  $var wire 1 ( rdy_out2 $end
  $var wire 1 ) vld_in2 $end
  $var wire 8 * data_in2 [7:0] $end
  $var wire 8 8 data_out2 [7:0] $end
  $var wire 1 9 rdy_in2 $end
  $var wire 1 : vld_out2 $end
  $var wire 1 + rdy_out3 $end
  $var wire 1 , vld_in3 $end
  $var wire 16 - data_in3 [15:0] $end
  $var wire 16 ; data_out3 [15:0] $end
  $var wire 1 < rdy_in3 $end
  $var wire 1 = vld_out3 $end
  $var wire 32 a PERIOD [31:0] $end
  $var wire 64 . count_64 [63:0] $end
  $var wire 64 0 count_16 [63:0] $end
  $var wire 64 2 count_8 [63:0] $end
  $scope module fifo1 $end
   $var wire 32 b WIDTH [31:0] $end
   $var wire 32 c DEPTH [31:0] $end
   $var wire 32 d PTR_WIDTH [31:0] $end
   $var wire 1 ` clk $end
   $var wire 1 # rst_n $end
   $var wire 1 $ rdy_out $end
   $var wire 1 % vld_in $end
   $var wire 64 & data_in [63:0] $end
   $var wire 64 4 data_out [63:0] $end
   $var wire 1 6 rdy_in $end
   $var wire 1 7 vld_out $end
   $var wire 32 d COUNT_WIDTH [31:0] $end
   $var wire 64 G buffer[0] [63:0] $end
   $var wire 64 I buffer[1] [63:0] $end
   $var wire 64 K buffer[2] [63:0] $end
   $var wire 64 M buffer[3] [63:0] $end
   $var wire 64 O buffer[4] [63:0] $end
   $var wire 4 > write_ptr [3:0] $end
   $var wire 4 ? read_ptr [3:0] $end
   $var wire 4 @ count [3:0] $end
   $var wire 4 Q next_read_ptr [3:0] $end
  $upscope $end
  $scope module fifo2 $end
   $var wire 32 e WIDTH [31:0] $end
   $var wire 32 f DEPTH [31:0] $end
   $var wire 32 g PTR_WIDTH [31:0] $end
   $var wire 1 ` clk $end
   $var wire 1 # rst_n $end
   $var wire 1 ( rdy_out $end
   $var wire 1 ) vld_in $end
   $var wire 8 * data_in [7:0] $end
   $var wire 8 8 data_out [7:0] $end
   $var wire 1 9 rdy_in $end
   $var wire 1 : vld_out $end
   $var wire 32 d COUNT_WIDTH [31:0] $end
   $var wire 8 R buffer[0] [7:0] $end
   $var wire 8 S buffer[1] [7:0] $end
   $var wire 8 T buffer[2] [7:0] $end
   $var wire 8 U buffer[3] [7:0] $end
   $var wire 3 A write_ptr [2:0] $end
   $var wire 3 B read_ptr [2:0] $end
   $var wire 4 C count [3:0] $end
   $var wire 3 V next_read_ptr [2:0] $end
  $upscope $end
  $scope module fifo3 $end
   $var wire 32 h WIDTH [31:0] $end
   $var wire 32 e DEPTH [31:0] $end
   $var wire 32 d PTR_WIDTH [31:0] $end
   $var wire 1 ` clk $end
   $var wire 1 # rst_n $end
   $var wire 1 + rdy_out $end
   $var wire 1 , vld_in $end
   $var wire 16 - data_in [15:0] $end
   $var wire 16 ; data_out [15:0] $end
   $var wire 1 < rdy_in $end
   $var wire 1 = vld_out $end
   $var wire 32 d COUNT_WIDTH [31:0] $end
   $var wire 16 W buffer[0] [15:0] $end
   $var wire 16 X buffer[1] [15:0] $end
   $var wire 16 Y buffer[2] [15:0] $end
   $var wire 16 Z buffer[3] [15:0] $end
   $var wire 16 [ buffer[4] [15:0] $end
   $var wire 16 \ buffer[5] [15:0] $end
   $var wire 16 ] buffer[6] [15:0] $end
   $var wire 16 ^ buffer[7] [15:0] $end
   $var wire 4 D write_ptr [3:0] $end
   $var wire 4 E read_ptr [3:0] $end
   $var wire 4 F count [3:0] $end
   $var wire 4 _ next_read_ptr [3:0] $end
  $upscope $end
 $upscope $end
$enddefinitions $end


#0
0#
0$
0%
b0000000000000000000000000000000000000000000000000000000000000000 &
0(
0)
b00000000 *
0+
0,
b0000000000000000 -
b0000000000000000000000000000000000000000000000000000000000000000 .
b0000000000000000000000000000000000000000000000000000000000000000 0
b0000000000000000000000000000000000000000000000000000000000000000 2
b0000000000000000000000000000000000000000000000000000000000000000 4
16
07
b00000000 8
19
0:
b0000000000000000 ;
1<
0=
b0000 >
b0000 ?
b0000 @
b000 A
b000 B
b0000 C
b0000 D
b0000 E
b0000 F
b0000000000000000000000000000000000000000000000000000000000000000 G
b0000000000000000000000000000000000000000000000000000000000000000 I
b0000000000000000000000000000000000000000000000000000000000000000 K
b0000000000000000000000000000000000000000000000000000000000000000 M
b0000000000000000000000000000000000000000000000000000000000000000 O
b0000 Q
b00000000 R
b00000000 S
b00000000 T
b00000000 U
b000 V
b0000000000000000 W
b0000000000000000 X
b0000000000000000 Y
b0000000000000000 Z
b0000000000000000 [
b0000000000000000 \
b0000000000000000 ]
b0000000000000000 ^
b0000 _
0`
b00000000000000000000000000001010 a
b00000000000000000000000001000000 b
b00000000000000000000000000000101 c
b00000000000000000000000000000011 d
b00000000000000000000000000001000 e
b00000000000000000000000000000100 f
b00000000000000000000000000000010 g
b00000000000000000000000000010000 h
#5000
1`
#10000
1#
0`
#15000
1`
#20000
0`
#25000
1`
#30000
1%
b0000000001000000100101000010110001111001011101100111001111000100 &
0`
#35000
b0000000001000000100101000010110001111001011101100111001111000100 4
17
b0001 >
b0001 @
b0000000001000000100101000010110001111001011101100111001111000100 G
1`
#40000
0%
0`
#45000
1`
#50000
1%
b1111000100000000000100000010010100001011000111100101110110011100 &
0`
#55000
b0010 >
b0010 @
b1111000100000000000100000010010100001011000111100101110110011100 I
1`
#60000
0%
0`
#65000
1`
#70000
1%
b1110110101010111101011001011100110011110111111011101010100000010 &
0`
#75000
b0011 >
b0011 @
b1110110101010111101011001011100110011110111111011101010100000010 K
1`
#80000
0%
0`
#85000
1`
#90000
1%
b1100000100011101111000101001110001001000110000101110000011100100 &
0`
#95000
b0100 >
b0100 @
b1100000100011101111000101001110001001000110000101110000011100100 M
1`
#100000
0%
0`
#105000
1`
#110000
1%
b0111101000001101100001001010010110010010000101111000001101111000 &
0`
#115000
06
b0000 >
b0101 @
b0111101000001101100001001010010110010010000101111000001101111000 O
1`
#120000
0%
b0000000000000000000000000000000000000000000000000000000000000001 .
0`
#125000
1`
#130000
1$
0`
#135000
b1111000100000000000100000010010100001011000111100101110110011100 4
16
b0001 ?
b0100 @
b0001 Q
1`
#140000
0$
b0000000000000000000000000000000000000000000000000000000000000010 .
0`
#145000
1`
#150000
1$
0`
#155000
b1110110101010111101011001011100110011110111111011101010100000010 4
b0010 ?
b0011 @
b0010 Q
1`
#160000
0$
b0000000000000000000000000000000000000000000000000000000000000011 .
0`
#165000
1`
#170000
1$
0`
#175000
b1100000100011101111000101001110001001000110000101110000011100100 4
b0011 ?
b0010 @
b0011 Q
1`
#180000
0$
b0000000000000000000000000000000000000000000000000000000000000100 .
0`
#185000
1`
#190000
1$
0`
#195000
b0111101000001101100001001010010110010010000101111000001101111000 4
b0100 ?
b0001 @
b0100 Q
1`
#200000
0$
b0000000000000000000000000000000000000000000000000000000000000101 .
0`
#205000
1`
#210000
1$
0`
#215000
b0000000001000000100101000010110001111001011101100111001111000100 4
07
b0000 ?
b0000 @
b0000 Q
1`
#220000
0$
0`
#225000
1`
#230000
1)
b10111100 *
0`
#235000
b10111100 8
1:
b001 A
b0001 C
b10111100 R
1`
#240000
0)
0`
#245000
1`
#250000
1)
b10110110 *
0`
#255000
b010 A
b0010 C
b10110110 S
1`
#260000
0)
0`
#265000
1`
#270000
1)
b11100100 *
0`
#275000
b011 A
b0011 C
b11100100 T
1`
#280000
0)
0`
#285000
1`
#290000
1)
b10110111 *
0`
#295000
09
b000 A
b0100 C
b10110111 U
1`
#300000
0)
b0000000000000000000000000000000000000000000000000000000000000001 2
0`
#305000
1`
#310000
1(
0`
#315000
b10110110 8
19
b001 B
b0011 C
b001 V
1`
#320000
0(
b0000000000000000000000000000000000000000000000000000000000000010 2
0`
#325000
1`
#330000
1(
0`
#335000
b11100100 8
b010 B
b0010 C
b010 V
1`
#340000
0(
b0000000000000000000000000000000000000000000000000000000000000011 2
0`
#345000
1`
#350000
1(
0`
#355000
b10110111 8
b011 B
b0001 C
b011 V
1`
#360000
0(
b0000000000000000000000000000000000000000000000000000000000000100 2
0`
#365000
1`
#370000
1(
0`
#375000
b10111100 8
0:
b000 B
b0000 C
b000 V
1`
#380000
0(
0`
#385000
1`
#390000
1,
b0111000101010011 -
0`
#395000
b0111000101010011 ;
1=
b0001 D
b0001 F
b0111000101010011 W
1`
#400000
0,
0`
#405000
1`
#410000
1,
b0001011100100001 -
0`
#415000
b0010 D
b0010 F
b0001011100100001 X
1`
#420000
0,
0`
#425000
1`
#430000
1,
b0111110111100001 -
0`
#435000
b0011 D
b0011 F
b0111110111100001 Y
1`
#440000
0,
0`
#445000
1`
#450000
1,
b1010111111000101 -
0`
#455000
b0100 D
b0100 F
b1010111111000101 Z
1`
#460000
0,
0`
#465000
1`
#470000
1,
b1111001110000010 -
0`
#475000
b0101 D
b0101 F
b1111001110000010 [
1`
#480000
0,
0`
#485000
1`
#490000
1,
b1111111101100010 -
0`
#495000
b0110 D
b0110 F
b1111111101100010 \
1`
#500000
0,
0`
#505000
1`
#510000
1,
b0001011000110101 -
0`
#515000
b0111 D
b0111 F
b0001011000110101 ]
1`
#520000
0,
0`
#525000
1`
#530000
1,
b1100100100010010 -
0`
#535000
0<
b0000 D
b1000 F
b1100100100010010 ^
1`
#540000
0,
b0000000000000000000000000000000000000000000000000000000000000001 0
0`
#545000
1`
#550000
1+
0`
#555000
b0001011100100001 ;
1<
b0001 E
b0111 F
b0001 _
1`
#560000
0+
b0000000000000000000000000000000000000000000000000000000000000010 0
0`
#565000
1`
#570000
1+
0`
#575000
b0111110111100001 ;
b0010 E
b0110 F
b0010 _
1`
#580000
0+
b0000000000000000000000000000000000000000000000000000000000000011 0
0`
#585000
1`
#590000
1+
0`
#595000
b1010111111000101 ;
b0011 E
b0101 F
b0011 _
1`
#600000
0+
b0000000000000000000000000000000000000000000000000000000000000100 0
0`
#605000
1`
#610000
1+
0`
#615000
b1111001110000010 ;
b0100 E
b0100 F
b0100 _
1`
#620000
0+
b0000000000000000000000000000000000000000000000000000000000000101 0
0`
#625000
1`
#630000
1+
0`
#635000
b1111111101100010 ;
b0101 E
b0011 F
b0101 _
1`
#640000
0+
b0000000000000000000000000000000000000000000000000000000000000110 0
0`
#645000
1`
#650000
1+
0`
#655000
b0001011000110101 ;
b0110 E
b0010 F
b0110 _
1`
#660000
0+
b0000000000000000000000000000000000000000000000000000000000000111 0
0`
#665000
1`
#670000
1+
0`
#675000
b1100100100010010 ;
b0111 E
b0001 F
b0111 _
1`
#680000
0+
b0000000000000000000000000000000000000000000000000000000000001000 0
0`
#685000
1`
#690000
1+
0`
#695000
b0111000101010011 ;
0=
b0000 E
b0000 F
b0000 _
1`
#700000
0+
0`
#705000
1`
#710000
1%
b1110001010100010101001100100101001100010111110011010101101010110 &
0`
#715000
b1110001010100010101001100100101001100010111110011010101101010110 4
17
b0001 >
b0001 @
b1110001010100010101001100100101001100010111110011010101101010110 G
1`
#720000
0%
0`
#725000
1`
#730000
1%
b0111000011001100011011101001100010110100001100100011101111111101 &
0`
#735000
b0010 >
b0010 @
b0111000011001100011011101001100010110100001100100011101111111101 I
1`
#740000
0%
0`
#745000
1`
#750000
1%
b1010100010100110000101010010100011011100011010110100000111110100 &
0`
#755000
b0011 >
b0011 @
b1010100010100110000101010010100011011100011010110100000111110100 K
1`
#760000
0%
b0000000000000000000000000000000000000000000000000000000000000110 .
0`
#765000
1`
#770000
1$
0`
#775000
b0111000011001100011011101001100010110100001100100011101111111101 4
b0001 ?
b0010 @
b0001 Q
1`
#780000
0$
b0000000000000000000000000000000000000000000000000000000000000111 .
0`
#785000
1`
#790000
1$
0`
#795000
b1010100010100110000101010010100011011100011010110100000111110100 4
b0010 ?
b0001 @
b0010 Q
1`
#800000
0$
0`
#805000
1`
#810000
1%
b1100110101111110110010100011100100000110101011011111010100111011 &
0`
#815000
b0100 >
b0010 @
b1100110101111110110010100011100100000110101011011111010100111011 M
1`
#820000
0%
0`
#825000
1`
#830000
1%
b0010110100111111001011001101000011000110011011010100110101011000 &
0`
#835000
b0000 >
b0011 @
b0010110100111111001011001101000011000110011011010100110101011000 O
1`
#840000
0%
0`
#845000
1`
#850000
1%
b1001101000000011111111110110111111101001110011110000010010110010 &
0`
#855000
b0001 >
b0100 @
b1001101000000011111111110110111111101001110011110000010010110010 G
1`
#860000
0%
0`
#865000
1`
#870000
1%
b0101001010011000110101100111001101010110110100010000100001011100 &
0`
#875000
06
b0010 >
b0101 @
b0101001010011000110101100111001101010110110100010000100001011100 I
1`
#880000
0%
b0000000000000000000000000000000000000000000000000000000000001000 .
0`
#885000
1`
#890000
1$
0`
#895000
b1100110101111110110010100011100100000110101011011111010100111011 4
16
b0011 ?
b0100 @
b0011 Q
1`
#900000
0$
b0000000000000000000000000000000000000000000000000000000000001001 .
0`
#905000
1`
#910000
1$
0`
#915000
b0010110100111111001011001101000011000110011011010100110101011000 4
b0100 ?
b0011 @
b0100 Q
1`
#920000
0$
b0000000000000000000000000000000000000000000000000000000000001010 .
0`
#925000
1`
#930000
1$
0`
#935000
b1001101000000011111111110110111111101001110011110000010010110010 4
b0000 ?
b0010 @
b0000 Q
1`
#940000
0$
b0000000000000000000000000000000000000000000000000000000000001011 .
0`
#945000
1`
#950000
1$
0`
#955000
b0101001010011000110101100111001101010110110100010000100001011100 4
b0001 ?
b0001 @
b0001 Q
1`
#960000
0$
b0000000000000000000000000000000000000000000000000000000000001100 .
0`
#965000
1`
#970000
1$
0`
#975000
b1010100010100110000101010010100011011100011010110100000111110100 4
07
b0010 ?
b0000 @
b0010 Q
1`
#980000
0$
0`
#985000
1`
#990000
1)
b00011110 *
0`
#995000
b00011110 8
1:
b001 A
b0001 C
b00011110 R
1`
#1000000
0)
0`
#1005000
1`
#1010000
1)
b10011110 *
0`
#1015000
b010 A
b0010 C
b10011110 S
1`
#1020000
0)
0`
#1025000
1`
#1030000
1)
0`
#1035000
b011 A
b0011 C
b10011110 T
1`
#1040000
0)
0`
#1045000
1`
#1050000
1)
b11101110 *
0`
#1055000
09
b000 A
b0100 C
b11101110 U
1`
#1060000
0)
0`
#1065000
1`
#1070000
1)
b11111111 *
0`
#1075000
1`
#1080000
0)
b0000000000000000000000000000000000000000000000000000000000000101 2
0`
#1085000
1`
#1090000
1(
0`
#1095000
b10011110 8
19
b001 B
b0011 C
b001 V
1`
#1100000
0(
b0000000000000000000000000000000000000000000000000000000000000110 2
0`
#1105000
1`
#1110000
1(
0`
#1115000
b010 B
b0010 C
b010 V
1`
#1120000
0(
b0000000000000000000000000000000000000000000000000000000000000111 2
0`
#1125000
1`
#1130000
1(
0`
#1135000
b11101110 8
b011 B
b0001 C
b011 V
1`
#1140000
0(
b0000000000000000000000000000000000000000000000000000000000001000 2
0`
#1145000
1`
#1150000
1(
0`
#1155000
b00011110 8
0:
b000 B
b0000 C
b000 V
1`
#1160000
0(
0`
#1165000
1`
#1170000
1+
0`
#1175000
1`
#1180000
0+
0`
