rtl/axi_fifo.sv

module axi_fifo 
#(
    parameter WIDTH=64, 
    parameter DEPTH=5,
    parameter PTR_WIDTH = $clog2(DEPTH)
    )
(
    input                           clk,
    input                           rst_n,
    input                           rdy_out,
    input                           vld_in,
    input        [WIDTH-1:0]        data_in,
    output logic [WIDTH-1:0]        data_out,
    output logic                    rdy_in,
    output logic                    vld_out
);

parameter COUNT_WIDTH = ($clog2(DEPTH)-1 > 3) ? $clog2(DEPTH)-1 : 3;

logic [WIDTH-1:0]      buffer [0:DEPTH-1];
logic [PTR_WIDTH:0]  write_ptr;
logic [PTR_WIDTH:0]  read_ptr;

logic [COUNT_WIDTH:0]  count;

initial begin
    write_ptr    = '0;
    read_ptr     = '0;
    count        = '0;
    data_out     = buffer[0];

    // Display error if WIDTH is 0 or less.
    if (WIDTH <= 0) begin
        $error("%m ** Illegal condition **, you used %d WIDTH", WIDTH);
    end
    // Display error if DEPTH is 0 or less.
    if (DEPTH <= 0) begin
        $error("%m ** Illegal condition **, you used %d DEPTH", DEPTH);
    end

end // end initial


always_comb begin
    vld_out        = !(count == 0);
    rdy_in         =  (count < DEPTH);
end

logic [PTR_WIDTH:0] next_read_ptr;

always_ff @(posedge clk) begin
    if (!rst_n) begin
        write_ptr    <= '0;
        read_ptr     <= '0;
        count        <= '0;
        data_out     <= buffer[0];
    end else begin 
        if (vld_in && rdy_in) begin
            buffer[write_ptr[PTR_WIDTH-1:0]] <= data_in;
            if (count == 0) begin
                data_out <= data_in;
            end
            write_ptr                        <= next_ptr_index(write_ptr);
        end
        if (vld_out && rdy_out) begin
            next_read_ptr = next_ptr_index(read_ptr);
            data_out  <= buffer[next_read_ptr[PTR_WIDTH-1:0]];
            read_ptr  <= next_read_ptr;
        end
        if (vld_in && rdy_in && vld_out && rdy_out) begin
            count <= count; 
        end else if (vld_in && rdy_in) begin
            count <= count + 1; 
        end else if (vld_out && rdy_out) begin
            count <= count - 1;
        end
    end
end

function [PTR_WIDTH:0] next_ptr_index(
    input [PTR_WIDTH:0] ptr
);

if (ptr >= (DEPTH-1)) begin
    return 0;
end else begin
    return ptr + 1;
end

endfunction


endmodule

tests/tb_axi_fifo/tb_axi_fifo.sv
`timescale 1ns/1ps

module tb_axi_fifo;

// Clock & reset
logic clk;
logic rst_n;

// Probe signals for three FIFOs: default, small, medium
// FIFO #1: default parameters (WIDTH=64, DEPTH=5)
logic                   rdy_out1, vld_in1;
logic [63:0]            data_in1;
logic [63:0]            data_out1;
logic                   rdy_in1,  vld_out1;

// FIFO #2: WIDTH=8, DEPTH=4
logic                   rdy_out2, vld_in2;
logic [7:0]             data_in2;
logic [7:0]             data_out2;
logic                   rdy_in2,  vld_out2;

// FIFO #3: WIDTH=16, DEPTH=8
logic                   rdy_out3, vld_in3;
logic [15:0]            data_in3;
logic [15:0]            data_out3;
logic                   rdy_in3,  vld_out3;

// Clock generator
localparam PERIOD = 10;
initial begin
clk = 0;
forever #(PERIOD/2) clk = ~clk;
end

// Necessary to create Waveform
initial begin
// Name as needed
$dumpfile("tb_axi_fifo.vcd");
$dumpvars(0);
end

// Instantiate FIFO #1: default parameters
axi_fifo #() fifo1 (
.clk      (clk),
.rst_n    (rst_n),
.rdy_out  (rdy_out1),
.vld_in   (vld_in1),
.data_in  (data_in1),
.data_out (data_out1),
.rdy_in   (rdy_in1),
.vld_out  (vld_out1)
);

// Instantiate FIFO #2: WIDTH=8, DEPTH=4
axi_fifo #( .WIDTH(8), .DEPTH(4) ) fifo2 (
.clk      (clk),
.rst_n    (rst_n),
.rdy_out  (rdy_out2),
.vld_in   (vld_in2),
.data_in  (data_in2),
.data_out (data_out2),
.rdy_in   (rdy_in2),
.vld_out  (vld_out2)
);

// Instantiate FIFO #3: WIDTH=16, DEPTH=8
axi_fifo #( .WIDTH(16), .DEPTH(8) ) fifo3 (
.clk      (clk),
.rst_n    (rst_n),
.rdy_out  (rdy_out3),
.vld_in   (vld_in3),
.data_in  (data_in3),
.data_out (data_out3),
.rdy_in   (rdy_in3),
.vld_out  (vld_out3)
);

logic [63:0] fifo_64 [$];
logic [15:0] fifo_16 [$];
logic [7:0]  fifo_8  [$];

logic [63:0] count_64;
logic [63:0] count_16;
logic [63:0] count_8;

initial begin
    count_64 = 0;
    count_16 = 0;
    count_8 = 0;
end

 

  // Task: enqueue N words into a given FIFO instance
  task automatic push_words;
    input  int          id;
    input  int          n;
    begin
        logic  [63:0] big_rand;
        logic  [7:0]  small_rand;
        logic  [15:0] med_rand;
        logic  [31:0] temp;
        int i;
        for (i=0; i<n; i++) begin
        case (id)
          1: begin
                // generate a pattern for FIFO1
                wait (rdy_in1); // ensure ready
                big_rand = {$urandom, $urandom};
                fifo_64.push_back(big_rand);
                @(negedge clk);
                data_in1 = fifo_64[$];
                vld_in1  = 1;
                @(negedge clk);
                vld_in1  = 0;
             end

          2: begin
                wait (rdy_in2);
                temp = $urandom;
                small_rand = temp[7:0];
                fifo_8.push_back(small_rand);
                @(negedge clk);
                data_in2 = fifo_8[$];
                vld_in2  = 1;
                @(negedge clk);
                vld_in2  = 0;
             end

          3: begin
                wait (rdy_in3);
                temp = $urandom;
                med_rand = temp[15:0];
                fifo_16.push_back(med_rand);
                @(negedge clk);
                data_in3 = fifo_16[$];
                vld_in3  = 1;
                @(negedge clk);
                vld_in3  = 0;
             end
        endcase
      end
    end
  endtask

  // Task: dequeue N words from a given FIFO instance and check correctness
  task automatic pop_and_check;
    input  int          id;
    input  int          n;
    begin

        int i;
        for (i=0; i<n; i++) begin
        case (id)
          1: begin
                // check valid and data
                assert (vld_out1) else $error("FIFO1 underflow on pop #%0d", i);
                assert (data_out1 == fifo_64[count_64])
                    else $error("FIFO1 data mismatch: got %h, expected %h", data_out1, fifo_64[count_64]);
                count_64 += 1;
                @(negedge clk);
                rdy_out1 = 1;
                @(negedge clk);
                rdy_out1 = 0;
             end

          2: begin
                // check valid and data
                assert (vld_out2) else $error("FIFO2 underflow on pop #%0d", i);
                assert (data_out2 == fifo_8[count_8])
                    else $error("FIFO2 data mismatch: got %h, expected %h", data_out2, fifo_8[count_8]);
                count_8 += 1;
                @(negedge clk);
                rdy_out2 = 1;
                @(negedge clk);
                rdy_out2 = 0;
             end

          3: begin
                // check valid and data
                assert (vld_out3) else $error("FIFO3 underflow on pop #%0d", i);
                assert (data_out3 == fifo_16[count_16])
                    else $error("FIFO3 data mismatch: got %h, expected %h", data_out3, fifo_16[count_16]);
                count_16 += 1;
                @(negedge clk);
                rdy_out3 = 1;
                @(negedge clk);
                rdy_out3 = 0;
             end
        endcase
      end
    end
  endtask



  // Main test sequence
  initial begin

    // Wait for reset deassertion
    rst_n = 0;
    @(negedge clk);
    rst_n = 1;
    @(negedge clk);

    // Test 1: Fill then drain each FIFO fully
    push_words(1, 5);     // FIFO1 depth=5
    pop_and_check(1, 5);

    push_words(2, 4);     // FIFO2 depth=4
    pop_and_check(2, 4);

    push_words(3, 8);     // FIFO3 depth=8
    pop_and_check(3, 8);

    // Test 2: Push/Pop interleaved, random counts
    push_words(1, 3);
    pop_and_check(1, 2);
    push_words(1, 4);
    pop_and_check(1, 5);

    // Test 3: Full/Empty flag checks
    // Attempt to overfill
    push_words(2, 4);
    @(negedge clk);
    vld_in2 = 1; data_in2 = 8'hFF;
    @(negedge clk);
    vld_in2 = 0;
    assert (!rdy_in2) else $error("FIFO2 allowed write when full");
    pop_and_check(2, 4);

    // Attempt to over-empty
    @(negedge clk);
    rdy_out3 = 1;
    @(negedge clk);
    rdy_out3 = 0;
    assert (!vld_out3) else $error("FIFO3 asserted valid when empty");

    $display("All tests passed.");
    $finish;
  end

endmodule

tests/tb_axi_fifo/tb_axi_fifo.vcd
$date
	Fri May  9 21:12:02 2025
$end
$version
	Icarus Verilog
$end
$timescale
	1ps
$end
$scope module tb_axi_fifo $end
$var wire 1 ! vld_out3 $end
$var wire 1 " vld_out2 $end
$var wire 1 # vld_out1 $end
$var wire 1 $ rdy_in3 $end
$var wire 1 % rdy_in2 $end
$var wire 1 & rdy_in1 $end
$var wire 16 ' data_out3 [15:0] $end
$var wire 8 ( data_out2 [7:0] $end
$var wire 64 ) data_out1 [63:0] $end
$var parameter 32 * PERIOD $end
$var reg 1 + clk $end
$var reg 64 , count_16 [63:0] $end
$var reg 64 - count_64 [63:0] $end
$var reg 64 . count_8 [63:0] $end
$var reg 64 / data_in1 [63:0] $end
$var reg 8 0 data_in2 [7:0] $end
$var reg 16 1 data_in3 [15:0] $end
$var reg 1 2 rdy_out1 $end
$var reg 1 3 rdy_out2 $end
$var reg 1 4 rdy_out3 $end
$var reg 1 5 rst_n $end
$var reg 1 6 vld_in1 $end
$var reg 1 7 vld_in2 $end
$var reg 1 8 vld_in3 $end
$scope module fifo1 $end
$var wire 1 + clk $end
$var wire 64 9 data_in [63:0] $end
$var wire 1 2 rdy_out $end
$var wire 1 5 rst_n $end
$var wire 1 6 vld_in $end
$var parameter 33 : COUNT_WIDTH $end
$var parameter 32 ; DEPTH $end
$var parameter 32 < PTR_WIDTH $end
$var parameter 32 = WIDTH $end
$var reg 4 > count [3:0] $end
$var reg 64 ? data_out [63:0] $end
$var reg 4 @ next_read_ptr [3:0] $end
$var reg 1 & rdy_in $end
$var reg 4 A read_ptr [3:0] $end
$var reg 1 # vld_out $end
$var reg 4 B write_ptr [3:0] $end
$scope function next_ptr_index $end
$var reg 4 C ptr [3:0] $end
$upscope $end
$upscope $end
$scope module fifo2 $end
$var wire 1 + clk $end
$var wire 8 D data_in [7:0] $end
$var wire 1 3 rdy_out $end
$var wire 1 5 rst_n $end
$var wire 1 7 vld_in $end
$var parameter 33 E COUNT_WIDTH $end
$var parameter 32 F DEPTH $end
$var parameter 32 G PTR_WIDTH $end
$var parameter 32 H WIDTH $end
$var reg 4 I count [3:0] $end
$var reg 8 J data_out [7:0] $end
$var reg 3 K next_read_ptr [2:0] $end
$var reg 1 % rdy_in $end
$var reg 3 L read_ptr [2:0] $end
$var reg 1 " vld_out $end
$var reg 3 M write_ptr [2:0] $end
$scope function next_ptr_index $end
$var reg 3 N ptr [2:0] $end
$upscope $end
$upscope $end
$scope module fifo3 $end
$var wire 1 + clk $end
$var wire 16 O data_in [15:0] $end
$var wire 1 4 rdy_out $end
$var wire 1 5 rst_n $end
$var wire 1 8 vld_in $end
$var parameter 33 P COUNT_WIDTH $end
$var parameter 32 Q DEPTH $end
$var parameter 32 R PTR_WIDTH $end
$var parameter 32 S WIDTH $end
$var reg 4 T count [3:0] $end
$var reg 16 U data_out [15:0] $end
$var reg 4 V next_read_ptr [3:0] $end
$var reg 1 $ rdy_in $end
$var reg 4 W read_ptr [3:0] $end
$var reg 1 ! vld_out $end
$var reg 4 X write_ptr [3:0] $end
$scope function next_ptr_index $end
$var reg 4 Y ptr [3:0] $end
$upscope $end
$upscope $end
$scope task pop_and_check $end
$scope begin $unm_blk_81 $end
$upscope $end
$upscope $end
$scope task push_words $end
$scope begin $unm_blk_76 $end
$upscope $end
$upscope $end
$upscope $end
$enddefinitions $end
$comment Show the parameter values. $end
$dumpall
b10000 S
b11 R
b1000 Q
b11 P
b1000 H
b10 G
b100 F
b11 E
b1000000 =
b11 <
b101 ;
b11 :
b1010 *
$end
#0
$dumpvars
bx Y
b0 X
b0 W
bx V
bx U
b0 T
bx O
bx N
b0 M
b0 L
bx K
bx J
b0 I
bx D
bx C
b0 B
b0 A
bx @
bx ?
b0 >
bx 9
x8
x7
x6
05
x4
x3
x2
bx 1
bx 0
bx /
b0 .
b0 -
b0 ,
0+
bx )
bx (
bx '
1&
1%
1$
0#
0"
0!
$end
#5000
1+
#10000
15
0+
#15000
1+
#20000
0+
#25000
1+
#30000
16
b1001001000010101001101010010010001000000100010010101111010000001 /
b1001001000010101001101010010010001000000100010010101111010000001 9
0+
#35000
1#
b1 >
b1 B
b0 C
1+
#40000
06
0+
#45000
1+
#50000
16
b10010000100110101100000100100110001111100000101011001100011 /
b10010000100110101100000100100110001111100000101011001100011 9
0+
#55000
b10 >
b10 B
b1001001000010101001101010010010001000000100010010101111010000001 )
b1001001000010101001101010010010001000000100010010101111010000001 ?
b1 C
1+
#60000
06
0+
#65000
1+
#70000
16
b1000011010111001011110110000110111000110110111111001100110001101 /
b1000011010111001011110110000110111000110110111111001100110001101 9
0+
#75000
b11 >
b11 B
b10 C
1+
#80000
06
0+
#85000
1+
#90000
16
b11001011000010100001000110010100001001001101110101001000010010 /
b11001011000010100001000110010100001001001101110101001000010010 9
0+
#95000
b100 >
b100 B
b11 C
1+
#100000
06
0+
#105000
1+
#110000
16
b1000000011110011111000110000000110000110110101111100110100001101 /
b1000000011110011111000110000000110000110110101111100110100001101 9
0+
#115000
0&
b101 >
b0 B
b100 C
1+
#120000
b1 -
06
0+
#125000
1+
#130000
12
0+
#135000
1&
b100 >
b1 A
b10010000100110101100000100100110001111100000101011001100011 )
b10010000100110101100000100100110001111100000101011001100011 ?
b1 @
b0 C
1+
#140000
b10 -
02
0+
#145000
1+
#150000
12
0+
#155000
b11 >
b10 A
b1000011010111001011110110000110111000110110111111001100110001101 )
b1000011010111001011110110000110111000110110111111001100110001101 ?
b10 @
b1 C
1+
#160000
b11 -
02
0+
#165000
1+
#170000
12
0+
#175000
b10 >
b11 A
b11001011000010100001000110010100001001001101110101001000010010 )
b11001011000010100001000110010100001001001101110101001000010010 ?
b11 @
b10 C
1+
#180000
b100 -
02
0+
#185000
1+
#190000
12
0+
#195000
b1 >
b100 A
b1000000011110011111000110000000110000110110101111100110100001101 )
b1000000011110011111000110000000110000110110101111100110100001101 ?
b100 @
b11 C
1+
#200000
b101 -
02
0+
#205000
1+
#210000
12
0+
#215000
0#
b0 >
b0 A
b1001001000010101001101010010010001000000100010010101111010000001 )
b1001001000010101001101010010010001000000100010010101111010000001 ?
b0 @
b100 C
1+
#220000
02
0+
#225000
1+
#230000
17
b1110110 0
b1110110 D
0+
#235000
1"
b1 I
b1 M
b0 N
1+
#240000
07
0+
#245000
1+
#250000
17
b111101 0
b111101 D
0+
#255000
b10 I
b10 M
b1110110 (
b1110110 J
b1 N
1+
#260000
07
0+
#265000
1+
#270000
17
b11101101 0
b11101101 D
0+
#275000
b11 I
b11 M
b10 N
1+
#280000
07
0+
#285000
1+
#290000
17
b10001100 0
b10001100 D
0+
#295000
0%
b100 I
b0 M
b11 N
1+
#300000
b1 .
07
0+
#305000
1+
#310000
13
0+
#315000
1%
b11 I
b1 L
b111101 (
b111101 J
b1 K
b0 N
1+
#320000
b10 .
03
0+
#325000
1+
#330000
13
0+
#335000
b10 I
b10 L
b11101101 (
b11101101 J
b10 K
b1 N
1+
#340000
b11 .
03
0+
#345000
1+
#350000
13
0+
#355000
b1 I
b11 L
b10001100 (
b10001100 J
b11 K
b10 N
1+
#360000
b100 .
03
0+
#365000
1+
#370000
13
0+
#375000
0"
b0 I
b0 L
b1110110 (
b1110110 J
b0 K
b11 N
1+
#380000
03
0+
#385000
1+
#390000
18
b1110100111111001 1
b1110100111111001 O
0+
#395000
1!
b1 T
b1 X
b0 Y
1+
#400000
08
0+
#405000
1+
#410000
18
b10010011000110 1
b10010011000110 O
0+
#415000
b10 T
b10 X
b1110100111111001 '
b1110100111111001 U
b1 Y
1+
#420000
08
0+
#425000
1+
#430000
18
b1000010011000101 1
b1000010011000101 O
0+
#435000
b11 T
b11 X
b10 Y
1+
#440000
08
0+
#445000
1+
#450000
18
b1101001010101010 1
b1101001010101010 O
0+
#455000
b100 T
b100 X
b11 Y
1+
#460000
08
0+
#465000
1+
#470000
18
b1111011111100101 1
b1111011111100101 O
0+
#475000
b101 T
b101 X
b100 Y
1+
#480000
08
0+
#485000
1+
#490000
18
b111001001110111 1
b111001001110111 O
0+
#495000
b110 T
b110 X
b101 Y
1+
#500000
08
0+
#505000
1+
#510000
18
b1101011000010010 1
b1101011000010010 O
0+
#515000
b111 T
b111 X
b110 Y
1+
#520000
08
0+
#525000
1+
#530000
18
b1101101110001111 1
b1101101110001111 O
0+
#535000
0$
b1000 T
b0 X
b111 Y
1+
#540000
b1 ,
08
0+
#545000
1+
#550000
14
0+
#555000
1$
b111 T
b1 W
b10010011000110 '
b10010011000110 U
b1 V
b0 Y
1+
#560000
b10 ,
04
0+
#565000
1+
#570000
14
0+
#575000
b110 T
b10 W
b1000010011000101 '
b1000010011000101 U
b10 V
b1 Y
1+
#580000
b11 ,
04
0+
#585000
1+
#590000
14
0+
#595000
b101 T
b11 W
b1101001010101010 '
b1101001010101010 U
b11 V
b10 Y
1+
#600000
b100 ,
04
0+
#605000
1+
#610000
14
0+
#615000
b100 T
b100 W
b1111011111100101 '
b1111011111100101 U
b100 V
b11 Y
1+
#620000
b101 ,
04
0+
#625000
1+
#630000
14
0+
#635000
b11 T
b101 W
b111001001110111 '
b111001001110111 U
b101 V
b100 Y
1+
#640000
b110 ,
04
0+
#645000
1+
#650000
14
0+
#655000
b10 T
b110 W
b1101011000010010 '
b1101011000010010 U
b110 V
b101 Y
1+
#660000
b111 ,
04
0+
#665000
1+
#670000
14
0+
#675000
b1 T
b111 W
b1101101110001111 '
b1101101110001111 U
b111 V
b110 Y
1+
#680000
b1000 ,
04
0+
#685000
1+
#690000
14
0+
#695000
0!
b0 T
b0 W
b1110100111111001 '
b1110100111111001 U
b0 V
b111 Y
1+
#700000
04
0+
#705000
1+
#710000
16
b1111100100110000011010011111001001100111011101101001011011001110 /
b1111100100110000011010011111001001100111011101101001011011001110 9
0+
#715000
1#
b1 >
b1 B
b0 C
1+
#720000
06
0+
#725000
1+
#730000
16
b111010000000000011110101110100001100010110010100100111011000101 /
b111010000000000011110101110100001100010110010100100111011000101 9
0+
#735000
b10 >
b10 B
b1111100100110000011010011111001001100111011101101001011011001110 )
b1111100100110000011010011111001001100111011101101001011011001110 ?
b1 C
1+
#740000
06
0+
#745000
1+
#750000
16
b1010111001011000010010010101110001011110100011100010100010111101 /
b1010111001011000010010010101110001011110100011100010100010111101 9
0+
#755000
b11 >
b11 B
b10 C
1+
#760000
b110 -
06
0+
#765000
1+
#770000
12
0+
#775000
b10 >
b1 A
b111010000000000011110101110100001100010110010100100111011000101 )
b111010000000000011110101110100001100010110010100100111011000101 ?
b1 @
b0 C
1+
#780000
b111 -
02
0+
#785000
1+
#790000
12
0+
#795000
b1 >
b10 A
b1010111001011000010010010101110001011110100011100010100010111101 )
b1010111001011000010010010101110001011110100011100010100010111101 ?
b10 @
b1 C
1+
#800000
02
0+
#805000
1+
#810000
16
b1011010101011010110000010110100110010101001110010011001100101 /
b1011010101011010110000010110100110010101001110010011001100101 9
0+
#815000
b10 >
b100 B
b11 C
1+
#820000
06
0+
#825000
1+
#830000
16
b11000111101111011000100110001110000101011100111000011100001010 /
b11000111101111011000100110001110000101011100111000011100001010 9
0+
#835000
b11 >
b0 B
b100 C
1+
#840000
06
0+
#845000
1+
#850000
16
b100000000111011001000101000000010010000011001000010000100100000 /
b100000000111011001000101000000010010000011001000010000100100000 9
0+
#855000
b100 >
b1 B
b0 C
1+
#860000
06
0+
#865000
1+
#870000
16
b1101010101111000010001011010101001001110110011001100110010011101 /
b1101010101111000010001011010101001001110110011001100110010011101 9
0+
#875000
0&
b101 >
b10 B
b1 C
1+
#880000
b1000 -
06
0+
#885000
1+
#890000
12
0+
#895000
1&
b100 >
b11 A
b1011010101011010110000010110100110010101001110010011001100101 )
b1011010101011010110000010110100110010101001110010011001100101 ?
b11 @
b10 C
1+
#900000
b1001 -
02
0+
#905000
1+
#910000
12
0+
#915000
b11 >
b100 A
b11000111101111011000100110001110000101011100111000011100001010 )
b11000111101111011000100110001110000101011100111000011100001010 ?
b100 @
b11 C
1+
#920000
b1010 -
02
0+
#925000
1+
#930000
12
0+
#935000
b10 >
b0 A
b100000000111011001000101000000010010000011001000010000100100000 )
b100000000111011001000101000000010010000011001000010000100100000 ?
b0 @
b100 C
1+
#940000
b1011 -
02
0+
#945000
1+
#950000
12
0+
#955000
b1 >
b1 A
b1101010101111000010001011010101001001110110011001100110010011101 )
b1101010101111000010001011010101001001110110011001100110010011101 ?
b1 @
b0 C
1+
#960000
b1100 -
02
0+
#965000
1+
#970000
12
0+
#975000
0#
b0 >
b10 A
b1010111001011000010010010101110001011110100011100010100010111101 )
b1010111001011000010010010101110001011110100011100010100010111101 ?
b10 @
b1 C
1+
#980000
02
0+
#985000
1+
#990000
17
b10010110 0
b10010110 D
0+
#995000
1"
b1 I
b1 M
b0 N
1+
#1000000
07
0+
#1005000
1+
#1010000
17
b10011 0
b10011 D
0+
#1015000
b10 I
b10 M
b10010110 (
b10010110 J
b1 N
1+
#1020000
07
0+
#1025000
1+
#1030000
17
b1101 0
b1101 D
0+
#1035000
b11 I
b11 M
b10 N
1+
#1040000
07
0+
#1045000
1+
#1050000
17
b1010011 0
b1010011 D
0+
#1055000
0%
b100 I
b0 M
b11 N
1+
#1060000
07
0+
#1065000
1+
#1070000
b11111111 0
b11111111 D
17
0+
#1075000
1+
#1080000
b101 .
07
0+
#1085000
1+
#1090000
13
0+
#1095000
1%
b11 I
b1 L
b10011 (
b10011 J
b1 K
b0 N
1+
#1100000
b110 .
03
0+
#1105000
1+
#1110000
13
0+
#1115000
b10 I
b10 L
b1101 (
b1101 J
b10 K
b1 N
1+
#1120000
b111 .
03
0+
#1125000
1+
#1130000
13
0+
#1135000
b1 I
b11 L
b1010011 (
b1010011 J
b11 K
b10 N
1+
#1140000
b1000 .
03
0+
#1145000
1+
#1150000
13
0+
#1155000
0"
b0 I
b0 L
b10010110 (
b10010110 J
b0 K
b11 N
1+
#1160000
03
0+
#1165000
1+
#1170000
14
0+
#1175000
b1 W
b10010011000110 '
b10010011000110 U
b1 V
b0 Y
1+
#1180000
04
0+
