rtl/axi_fifo.sv

module axi_fifo 
#(
    parameter WIDTH=64, 
    parameter MIN_DEPTH=4
)
(
    input                           clk,
    input                           rst_n,
    input                           rdy_out,
    input                           vld_in,
    input        [WIDTH-1:0]        data_in,
    output logic [WIDTH-1:0]        data_out,
    output logic                    rdy_in,
    output logic                    vld_out
);

parameter DEPTH = 2**$clog2(MIN_DEPTH);
parameter PTR_WIDTH = $clog2(DEPTH);

logic [WIDTH-1:0]    buffer [0:DEPTH-1];
logic [PTR_WIDTH:0]  write_ptr;
logic [PTR_WIDTH:0]  read_ptr;

initial begin
    write_ptr    = '0;
    read_ptr     = '0;
    data_out     = '0;
    for (int i = 0; i < DEPTH; i++) begin
        buffer[i] = 0;
    end

    // Display error if WIDTH is 0 or less.
    if (WIDTH <= 0) begin
        $error("%m ** Illegal condition **, you used %d WIDTH", WIDTH);
    end
    // Display error if DEPTH is 0 or less.
    if (DEPTH <= 0) begin
        $error("%m ** Illegal condition **, you used %d DEPTH", DEPTH);
    end

end


always_comb begin
    vld_out        = write_ptr != read_ptr;
    rdy_in         = !(write_ptr[PTR_WIDTH] != read_ptr[PTR_WIDTH] && write_ptr[PTR_WIDTH-1:0] == read_ptr[PTR_WIDTH-1:0]);
end

logic [PTR_WIDTH:0] next_read_ptr;

always_ff @(posedge clk) begin
    if (!rst_n) begin
        write_ptr    <= '0;
        read_ptr     <= '0;
        data_out     <= '0;
    end else begin 

        if (vld_in && rdy_in) begin
            buffer[write_ptr[PTR_WIDTH-1:0]] <= data_in;
            write_ptr <= write_ptr + 1;
            if (!vld_out) begin
                data_out  <= data_in;
            end
        end

        if (vld_out && rdy_out) begin
            next_read_ptr = read_ptr + 1;
            data_out  <= buffer[next_read_ptr[PTR_WIDTH-1:0]];
            read_ptr  <= next_read_ptr;
        end
    end
end


endmodule

tests/tb_axi_fifo/tb_axi_fifo.sv
`timescale 1ns/1ps

module tb_axi_fifo;

// Clock & reset
logic clk;
logic rst_n;

// Probe signals for three FIFOs: default, small, medium
// FIFO #1: default parameters (WIDTH=64, DEPTH=5)
logic                   rdy_out1, vld_in1;
logic [63:0]            data_in1;
logic [63:0]            data_out1;
logic                   rdy_in1,  vld_out1;

// FIFO #2: WIDTH=8, DEPTH=4
logic                   rdy_out2, vld_in2;
logic [7:0]             data_in2;
logic [7:0]             data_out2;
logic                   rdy_in2,  vld_out2;

// FIFO #3: WIDTH=16, DEPTH=8
logic                   rdy_out3, vld_in3;
logic [15:0]            data_in3;
logic [15:0]            data_out3;
logic                   rdy_in3,  vld_out3;

// Clock generator
localparam PERIOD = 10;
initial begin
clk = 0;
forever #(PERIOD/2) clk = ~clk;
end

// Necessary to create Waveform
initial begin
// Name as needed
$dumpfile("tb_axi_fifo.vcd");
$dumpvars(0);
end

// Instantiate FIFO #1: default parameters
axi_fifo #(.WIDTH(64), .MIN_DEPTH(16)) fifo1 (
.clk      (clk),
.rst_n    (rst_n),
.rdy_out  (rdy_out1),
.vld_in   (vld_in1),
.data_in  (data_in1),
.data_out (data_out1),
.rdy_in   (rdy_in1),
.vld_out  (vld_out1)
);

// Instantiate FIFO #2: WIDTH=8, DEPTH=4
axi_fifo #( .WIDTH(8), .MIN_DEPTH(4) ) fifo2 (
.clk      (clk),
.rst_n    (rst_n),
.rdy_out  (rdy_out2),
.vld_in   (vld_in2),
.data_in  (data_in2),
.data_out (data_out2),
.rdy_in   (rdy_in2),
.vld_out  (vld_out2)
);

// Instantiate FIFO #3: WIDTH=16, DEPTH=8
axi_fifo #( .WIDTH(16), .MIN_DEPTH(8) ) fifo3 (
.clk      (clk),
.rst_n    (rst_n),
.rdy_out  (rdy_out3),
.vld_in   (vld_in3),
.data_in  (data_in3),
.data_out (data_out3),
.rdy_in   (rdy_in3),
.vld_out  (vld_out3)
);

logic [63:0] fifo_64 [$];
logic [15:0] fifo_16 [$];
logic [7:0]  fifo_8  [$];

logic [63:0] count_64;
logic [63:0] count_16;
logic [63:0] count_8;

initial begin
    count_64 = 0;
    count_16 = 0;
    count_8 = 0;
end

 

  // Task: enqueue N words into a given FIFO instance
  task automatic push_words;
    input  int          id;
    input  int          n;
    begin
        logic  [63:0] big_rand;
        logic  [7:0]  small_rand;
        logic  [15:0] med_rand;
        logic  [31:0] temp;
        int i;
        for (i=0; i<n; i++) begin
        case (id)
          1: begin
                // generate a pattern for FIFO1
                wait (rdy_in1); // ensure ready
                big_rand = {$urandom, $urandom};
                fifo_64.push_back(big_rand);
                @(negedge clk);
                data_in1 = fifo_64[$];
                vld_in1  = 1;
                @(negedge clk);
                vld_in1  = 0;
             end

          2: begin
                wait (rdy_in2);
                temp = $urandom;
                small_rand = temp[7:0];
                fifo_8.push_back(small_rand);
                @(negedge clk);
                data_in2 = fifo_8[$];
                vld_in2  = 1;
                @(negedge clk);
                vld_in2  = 0;
             end

          3: begin
                wait (rdy_in3);
                temp = $urandom;
                med_rand = temp[15:0];
                fifo_16.push_back(med_rand);
                @(negedge clk);
                data_in3 = fifo_16[$];
                vld_in3  = 1;
                @(negedge clk);
                vld_in3  = 0;
             end
        endcase
      end
    end
  endtask

  // Task: dequeue N words from a given FIFO instance and check correctness
  task automatic pop_and_check;
    input  int          id;
    input  int          n;
    begin

        int i;
        for (i=0; i<n; i++) begin
        case (id)
          1: begin
                // check valid and data
                assert (vld_out1) else $error("FIFO1 underflow on pop #%0d", i);
                assert (data_out1 == fifo_64[count_64])
                    else $error("FIFO1 data mismatch: got %h, expected %h", data_out1, fifo_64[count_64]);
                count_64 += 1;
                @(negedge clk);
                rdy_out1 = 1;
                @(negedge clk);
                rdy_out1 = 0;
             end

          2: begin
                // check valid and data
                assert (vld_out2) else $error("FIFO2 underflow on pop #%0d", i);
                assert (data_out2 == fifo_8[count_8])
                    else $error("FIFO2 data mismatch: got %h, expected %h", data_out2, fifo_8[count_8]);
                count_8 += 1;
                @(negedge clk);
                rdy_out2 = 1;
                @(negedge clk);
                rdy_out2 = 0;
             end

          3: begin
                // check valid and data
                assert (vld_out3) else $error("FIFO3 underflow on pop #%0d", i);
                assert (data_out3 == fifo_16[count_16])
                    else $error("FIFO3 data mismatch: got %h, expected %h", data_out3, fifo_16[count_16]);
                count_16 += 1;
                @(negedge clk);
                rdy_out3 = 1;
                @(negedge clk);
                rdy_out3 = 0;
             end
        endcase
      end
    end
  endtask



  // Main test sequence
  initial begin

    // Wait for reset deassertion
    rst_n = 0;
    @(negedge clk);
    rst_n = 1;
    @(negedge clk);

    // Test 1: Fill then drain each FIFO fully
    push_words(1, 16);     // FIFO1 depth=16
    pop_and_check(1, 16);

    push_words(2, 4);     // FIFO2 depth=4
    pop_and_check(2, 4);

    push_words(3, 8);     // FIFO3 depth=8
    pop_and_check(3, 8);

    // Test 2: Push/Pop interleaved, random counts
    push_words(1, 3);
    pop_and_check(1, 2);
    push_words(1, 4);
    pop_and_check(1, 5);

    // Test 3: Full/Empty flag checks
    // Attempt to overfill
    push_words(2, 4);
    @(negedge clk);
    vld_in2 = 1; data_in2 = 8'hFF;
    @(negedge clk);
    vld_in2 = 0;
    assert (!rdy_in2) else $error("FIFO2 allowed write when full");
    pop_and_check(2, 4);

    // Attempt to over-empty
    @(negedge clk);
    rdy_out3 = 1;
    @(negedge clk);
    rdy_out3 = 0;
    assert (!vld_out3) else $error("FIFO3 asserted valid when empty");

    $display("All tests passed.");
    $finish;
  end

endmodule

tests/tb_axi_fifo/tb_axi_fifo.vcd
$date
	Mon May 12 18:56:54 2025
$end
$version
	Icarus Verilog
$end
$timescale
	1ps
$end
$scope module tb_axi_fifo $end
$var wire 1 ! vld_out3 $end
$var wire 1 " vld_out2 $end
$var wire 1 # vld_out1 $end
$var wire 1 $ rdy_in3 $end
$var wire 1 % rdy_in2 $end
$var wire 1 & rdy_in1 $end
$var wire 16 ' data_out3 [15:0] $end
$var wire 8 ( data_out2 [7:0] $end
$var wire 64 ) data_out1 [63:0] $end
$var parameter 32 * PERIOD $end
$var reg 1 + clk $end
$var reg 64 , count_16 [63:0] $end
$var reg 64 - count_64 [63:0] $end
$var reg 64 . count_8 [63:0] $end
$var reg 64 / data_in1 [63:0] $end
$var reg 8 0 data_in2 [7:0] $end
$var reg 16 1 data_in3 [15:0] $end
$var reg 1 2 rdy_out1 $end
$var reg 1 3 rdy_out2 $end
$var reg 1 4 rdy_out3 $end
$var reg 1 5 rst_n $end
$var reg 1 6 vld_in1 $end
$var reg 1 7 vld_in2 $end
$var reg 1 8 vld_in3 $end
$scope module fifo1 $end
$var wire 1 + clk $end
$var wire 64 9 data_in [63:0] $end
$var wire 1 2 rdy_out $end
$var wire 1 5 rst_n $end
$var wire 1 6 vld_in $end
$var parameter 32 : DEPTH $end
$var parameter 32 ; MIN_DEPTH $end
$var parameter 32 < PTR_WIDTH $end
$var parameter 32 = WIDTH $end
$var reg 64 > data_out [63:0] $end
$var reg 5 ? next_read_ptr [4:0] $end
$var reg 1 & rdy_in $end
$var reg 5 @ read_ptr [4:0] $end
$var reg 1 # vld_out $end
$var reg 5 A write_ptr [4:0] $end
$scope begin $ivl_for_loop0 $end
$var integer 32 B i [31:0] $end
$upscope $end
$upscope $end
$scope module fifo2 $end
$var wire 1 + clk $end
$var wire 8 C data_in [7:0] $end
$var wire 1 3 rdy_out $end
$var wire 1 5 rst_n $end
$var wire 1 7 vld_in $end
$var parameter 32 D DEPTH $end
$var parameter 32 E MIN_DEPTH $end
$var parameter 32 F PTR_WIDTH $end
$var parameter 32 G WIDTH $end
$var reg 8 H data_out [7:0] $end
$var reg 3 I next_read_ptr [2:0] $end
$var reg 1 % rdy_in $end
$var reg 3 J read_ptr [2:0] $end
$var reg 1 " vld_out $end
$var reg 3 K write_ptr [2:0] $end
$scope begin $ivl_for_loop0 $end
$var integer 32 L i [31:0] $end
$upscope $end
$upscope $end
$scope module fifo3 $end
$var wire 1 + clk $end
$var wire 16 M data_in [15:0] $end
$var wire 1 4 rdy_out $end
$var wire 1 5 rst_n $end
$var wire 1 8 vld_in $end
$var parameter 32 N DEPTH $end
$var parameter 32 O MIN_DEPTH $end
$var parameter 32 P PTR_WIDTH $end
$var parameter 32 Q WIDTH $end
$var reg 16 R data_out [15:0] $end
$var reg 4 S next_read_ptr [3:0] $end
$var reg 1 $ rdy_in $end
$var reg 4 T read_ptr [3:0] $end
$var reg 1 ! vld_out $end
$var reg 4 U write_ptr [3:0] $end
$scope begin $ivl_for_loop0 $end
$var integer 32 V i [31:0] $end
$upscope $end
$upscope $end
$scope task pop_and_check $end
$scope begin $unm_blk_83 $end
$upscope $end
$upscope $end
$scope task push_words $end
$scope begin $unm_blk_78 $end
$upscope $end
$upscope $end
$upscope $end
$enddefinitions $end
$comment Show the parameter values. $end
$dumpall
b10000 Q
b11 P
b1000 O
b1000 N
b1000 G
b10 F
b100 E
b100 D
b1000000 =
b100 <
b10000 ;
b10000 :
b1010 *
$end
#0
$dumpvars
b1000 V
b0 U
b0 T
bx S
b0 R
bx M
b100 L
b0 K
b0 J
bx I
b0 H
bx C
b10000 B
b0 A
b0 @
bx ?
b0 >
bx 9
x8
x7
x6
05
x4
x3
x2
bx 1
bx 0
bx /
b0 .
b0 -
b0 ,
0+
b0 )
b0 (
b0 '
1&
1%
1$
0#
0"
0!
$end
#5000
1+
#10000
15
0+
#15000
1+
#20000
0+
#25000
1+
#30000
16
b1001001000010101001101010010010001000000100010010101111010000001 /
b1001001000010101001101010010010001000000100010010101111010000001 9
0+
#35000
1#
b1001001000010101001101010010010001000000100010010101111010000001 )
b1001001000010101001101010010010001000000100010010101111010000001 >
b1 A
1+
#40000
06
0+
#45000
1+
#50000
16
b10010000100110101100000100100110001111100000101011001100011 /
b10010000100110101100000100100110001111100000101011001100011 9
0+
#55000
b10 A
1+
#60000
06
0+
#65000
1+
#70000
16
b1000011010111001011110110000110111000110110111111001100110001101 /
b1000011010111001011110110000110111000110110111111001100110001101 9
0+
#75000
b11 A
1+
#80000
06
0+
#85000
1+
#90000
16
b11001011000010100001000110010100001001001101110101001000010010 /
b11001011000010100001000110010100001001001101110101001000010010 9
0+
#95000
b100 A
1+
#100000
06
0+
#105000
1+
#110000
16
b1000000011110011111000110000000110000110110101111100110100001101 /
b1000000011110011111000110000000110000110110101111100110100001101 9
0+
#115000
b101 A
1+
#120000
06
0+
#125000
1+
#130000
16
b1011101100100011111100010111011010011110100011011100110100111101 /
b1011101100100011111100010111011010011110100011011100110100111101 9
0+
#135000
b110 A
1+
#140000
06
0+
#145000
1+
#150000
16
b1111011011010100010101111110110111000110001011011111011110001100 /
b1111011011010100010101111110110111000110001011011111011110001100 9
0+
#155000
b111 A
1+
#160000
06
0+
#165000
1+
#170000
16
b1111110011111101111010011111100101100011001101110010010011000110 /
b1111110011111101111010011111100101100011001101110010010011000110 9
0+
#175000
b1000 A
1+
#180000
06
0+
#185000
1+
#190000
16
b110001011110111100001001100010101010101000100111101001010101010 /
b110001011110111100001001100010101010101000100111101001010101010 9
0+
#195000
b1001 A
1+
#200000
06
0+
#205000
1+
#210000
16
b1111001010101111111101111110010100111011110100100111001001110111 /
b1111001010101111111101111110010100111011110100100111001001110111 9
0+
#215000
b1010 A
1+
#220000
06
0+
#225000
1+
#230000
16
b100100110010110101100001001011000111111011001101101110001111 /
b100100110010110101100001001011000111111011001101101110001111 9
0+
#235000
b1011 A
1+
#240000
06
0+
#245000
1+
#250000
16
b1111100100110000011010011111001001100111011101101001011011001110 /
b1111100100110000011010011111001001100111011101101001011011001110 9
0+
#255000
b1100 A
1+
#260000
06
0+
#265000
1+
#270000
16
b111010000000000011110101110100001100010110010100100111011000101 /
b111010000000000011110101110100001100010110010100100111011000101 9
0+
#275000
b1101 A
1+
#280000
06
0+
#285000
1+
#290000
16
b1010111001011000010010010101110001011110100011100010100010111101 /
b1010111001011000010010010101110001011110100011100010100010111101 9
0+
#295000
b1110 A
1+
#300000
06
0+
#305000
1+
#310000
16
b1011010101011010110000010110100110010101001110010011001100101 /
b1011010101011010110000010110100110010101001110010011001100101 9
0+
#315000
b1111 A
1+
#320000
06
0+
#325000
1+
#330000
16
b11000111101111011000100110001110000101011100111000011100001010 /
b11000111101111011000100110001110000101011100111000011100001010 9
0+
#335000
0&
b10000 A
1+
#340000
b1 -
06
0+
#345000
1+
#350000
12
0+
#355000
1&
b1 @
b10010000100110101100000100100110001111100000101011001100011 )
b10010000100110101100000100100110001111100000101011001100011 >
b1 ?
1+
#360000
b10 -
02
0+
#365000
1+
#370000
12
0+
#375000
b10 @
b1000011010111001011110110000110111000110110111111001100110001101 )
b1000011010111001011110110000110111000110110111111001100110001101 >
b10 ?
1+
#380000
b11 -
02
0+
#385000
1+
#390000
12
0+
#395000
b11 @
b11001011000010100001000110010100001001001101110101001000010010 )
b11001011000010100001000110010100001001001101110101001000010010 >
b11 ?
1+
#400000
b100 -
02
0+
#405000
1+
#410000
12
0+
#415000
b100 @
b1000000011110011111000110000000110000110110101111100110100001101 )
b1000000011110011111000110000000110000110110101111100110100001101 >
b100 ?
1+
#420000
b101 -
02
0+
#425000
1+
#430000
12
0+
#435000
b101 @
b1011101100100011111100010111011010011110100011011100110100111101 )
b1011101100100011111100010111011010011110100011011100110100111101 >
b101 ?
1+
#440000
b110 -
02
0+
#445000
1+
#450000
12
0+
#455000
b110 @
b1111011011010100010101111110110111000110001011011111011110001100 )
b1111011011010100010101111110110111000110001011011111011110001100 >
b110 ?
1+
#460000
b111 -
02
0+
#465000
1+
#470000
12
0+
#475000
b111 @
b1111110011111101111010011111100101100011001101110010010011000110 )
b1111110011111101111010011111100101100011001101110010010011000110 >
b111 ?
1+
#480000
b1000 -
02
0+
#485000
1+
#490000
12
0+
#495000
b1000 @
b110001011110111100001001100010101010101000100111101001010101010 )
b110001011110111100001001100010101010101000100111101001010101010 >
b1000 ?
1+
#500000
b1001 -
02
0+
#505000
1+
#510000
12
0+
#515000
b1001 @
b1111001010101111111101111110010100111011110100100111001001110111 )
b1111001010101111111101111110010100111011110100100111001001110111 >
b1001 ?
1+
#520000
b1010 -
02
0+
#525000
1+
#530000
12
0+
#535000
b1010 @
b100100110010110101100001001011000111111011001101101110001111 )
b100100110010110101100001001011000111111011001101101110001111 >
b1010 ?
1+
#540000
b1011 -
02
0+
#545000
1+
#550000
12
0+
#555000
b1011 @
b1111100100110000011010011111001001100111011101101001011011001110 )
b1111100100110000011010011111001001100111011101101001011011001110 >
b1011 ?
1+
#560000
b1100 -
02
0+
#565000
1+
#570000
12
0+
#575000
b1100 @
b111010000000000011110101110100001100010110010100100111011000101 )
b111010000000000011110101110100001100010110010100100111011000101 >
b1100 ?
1+
#580000
b1101 -
02
0+
#585000
1+
#590000
12
0+
#595000
b1101 @
b1010111001011000010010010101110001011110100011100010100010111101 )
b1010111001011000010010010101110001011110100011100010100010111101 >
b1101 ?
1+
#600000
b1110 -
02
0+
#605000
1+
#610000
12
0+
#615000
b1110 @
b1011010101011010110000010110100110010101001110010011001100101 )
b1011010101011010110000010110100110010101001110010011001100101 >
b1110 ?
1+
#620000
b1111 -
02
0+
#625000
1+
#630000
12
0+
#635000
b1111 @
b11000111101111011000100110001110000101011100111000011100001010 )
b11000111101111011000100110001110000101011100111000011100001010 >
b1111 ?
1+
#640000
b10000 -
02
0+
#645000
1+
#650000
12
0+
#655000
0#
b10000 @
b1001001000010101001101010010010001000000100010010101111010000001 )
b1001001000010101001101010010010001000000100010010101111010000001 >
b10000 ?
1+
#660000
02
0+
#665000
1+
#670000
17
b10000000 0
b10000000 C
0+
#675000
1"
b10000000 (
b10000000 H
b1 K
1+
#680000
07
0+
#685000
1+
#690000
17
b100000 0
b100000 C
0+
#695000
b10 K
1+
#700000
07
0+
#705000
1+
#710000
17
b10101010 0
b10101010 C
0+
#715000
b11 K
1+
#720000
07
0+
#725000
1+
#730000
17
b10011101 0
b10011101 C
0+
#735000
0%
b100 K
1+
#740000
b1 .
07
0+
#745000
1+
#750000
13
0+
#755000
1%
b1 J
b100000 (
b100000 H
b1 I
1+
#760000
b10 .
03
0+
#765000
1+
#770000
13
0+
#775000
b10 J
b10101010 (
b10101010 H
b10 I
1+
#780000
b11 .
03
0+
#785000
1+
#790000
13
0+
#795000
b11 J
b10011101 (
b10011101 H
b11 I
1+
#800000
b100 .
03
0+
#805000
1+
#810000
13
0+
#815000
0"
b100 J
b10000000 (
b10000000 H
b100 I
1+
#820000
03
0+
#825000
1+
#830000
18
b11111010010110 1
b11111010010110 M
0+
#835000
1!
b11111010010110 '
b11111010010110 R
b1 U
1+
#840000
08
0+
#845000
1+
#850000
18
b1011100000010011 1
b1011100000010011 M
0+
#855000
b10 U
1+
#860000
08
0+
#865000
1+
#870000
18
b11100000001101 1
b11100000001101 M
0+
#875000
b11 U
1+
#880000
08
0+
#885000
1+
#890000
18
b1101011001010011 1
b1101011001010011 M
0+
#895000
b100 U
1+
#900000
08
0+
#905000
1+
#910000
18
b1101110101101011 1
b1101110101101011 M
0+
#915000
b101 U
1+
#920000
08
0+
#925000
1+
#930000
18
b10101011010101 1
b10101011010101 M
0+
#935000
b110 U
1+
#940000
08
0+
#945000
1+
#950000
18
b100101000000010 1
b100101000000010 M
0+
#955000
b111 U
1+
#960000
08
0+
#965000
1+
#970000
18
b11111010101110 1
b11111010101110 M
0+
#975000
0$
b1000 U
1+
#980000
b1 ,
08
0+
#985000
1+
#990000
14
0+
#995000
1$
b1 T
b1011100000010011 '
b1011100000010011 R
b1 S
1+
#1000000
b10 ,
04
0+
#1005000
1+
#1010000
14
0+
#1015000
b10 T
b11100000001101 '
b11100000001101 R
b10 S
1+
#1020000
b11 ,
04
0+
#1025000
1+
#1030000
14
0+
#1035000
b11 T
b1101011001010011 '
b1101011001010011 R
b11 S
1+
#1040000
b100 ,
04
0+
#1045000
1+
#1050000
14
0+
#1055000
b100 T
b1101110101101011 '
b1101110101101011 R
b100 S
1+
#1060000
b101 ,
04
0+
#1065000
1+
#1070000
14
0+
#1075000
b101 T
b10101011010101 '
b10101011010101 R
b101 S
1+
#1080000
b110 ,
04
0+
#1085000
1+
#1090000
14
0+
#1095000
b110 T
b100101000000010 '
b100101000000010 R
b110 S
1+
#1100000
b111 ,
04
0+
#1105000
1+
#1110000
14
0+
#1115000
b111 T
b11111010101110 '
b11111010101110 R
b111 S
1+
#1120000
b1000 ,
04
0+
#1125000
1+
#1130000
14
0+
#1135000
0!
b1000 T
b11111010010110 '
b11111010010110 R
b1000 S
1+
#1140000
04
0+
#1145000
1+
#1150000
16
b1000111011111111111010010001110101100111110001010111001011001111 /
b1000111011111111111010010001110101100111110001010111001011001111 9
0+
#1155000
1#
b1000111011111111111010010001110101100111110001010111001011001111 )
b1000111011111111111010010001110101100111110001010111001011001111 >
b10001 A
1+
#1160000
06
0+
#1165000
1+
#1170000
16
b1001000110000100010010010010001110000101000010010110010100001010 /
b1001000110000100010010010010001110000101000010010110010100001010 9
0+
#1175000
b10010 A
1+
#1180000
06
0+
#1185000
1+
#1190000
16
b110010101110011000010101100101000011110001100010100110000111100 /
b110010101110011000010101100101000011110001100010100110000111100 9
0+
#1195000
b10011 A
1+
#1200000
b10001 -
06
0+
#1205000
1+
#1210000
12
0+
#1215000
b10001 @
b1001000110000100010010010010001110000101000010010110010100001010 )
b1001000110000100010010010010001110000101000010010110010100001010 >
b10001 ?
1+
#1220000
b10010 -
02
0+
#1225000
1+
#1230000
12
0+
#1235000
b10010 @
b110010101110011000010101100101000011110001100010100110000111100 )
b110010101110011000010101100101000011110001100010100110000111100 >
b10010 ?
1+
#1240000
02
0+
#1245000
1+
#1250000
16
b1111100101101000101111011111001011000101001011100110000110001010 /
b1111100101101000101111011111001011000101001011100110000110001010 9
0+
#1255000
b10100 A
1+
#1260000
06
0+
#1265000
1+
#1270000
16
b1010000011000100101100110100000101101100010010110011010011011000 /
b1010000011000100101100110100000101101100010010110011010011011000 9
0+
#1275000
b10101 A
1+
#1280000
06
0+
#1285000
1+
#1290000
16
b1011110000100000111100110111100001000100100010100001001010001001 /
b1011110000100000111100110111100001000100100010100001001010001001 9
0+
#1295000
b10110 A
1+
#1300000
06
0+
#1305000
1+
#1310000
16
b1111010111000101000011011110101111011011000000100110010110110110 /
b1111010111000101000011011110101111011011000000100110010110110110 9
0+
#1315000
b10111 A
1+
#1320000
b10011 -
06
0+
#1325000
1+
#1330000
12
0+
#1335000
b10011 @
b1111100101101000101111011111001011000101001011100110000110001010 )
b1111100101101000101111011111001011000101001011100110000110001010 >
b10011 ?
1+
#1340000
b10100 -
02
0+
#1345000
1+
#1350000
12
0+
#1355000
b10100 @
b1010000011000100101100110100000101101100010010110011010011011000 )
b1010000011000100101100110100000101101100010010110011010011011000 >
b10100 ?
1+
#1360000
b10101 -
02
0+
#1365000
1+
#1370000
12
0+
#1375000
b10101 @
b1011110000100000111100110111100001000100100010100001001010001001 )
b1011110000100000111100110111100001000100100010100001001010001001 >
b10101 ?
1+
#1380000
b10110 -
02
0+
#1385000
1+
#1390000
12
0+
#1395000
b10110 @
b1111010111000101000011011110101111011011000000100110010110110110 )
b1111010111000101000011011110101111011011000000100110010110110110 >
b10110 ?
1+
#1400000
b10111 -
02
0+
#1405000
1+
#1410000
12
0+
#1415000
0#
b10111 @
b1111110011111101111010011111100101100011001101110010010011000110 )
b1111110011111101111010011111100101100011001101110010010011000110 >
b10111 ?
1+
#1420000
02
0+
#1425000
1+
#1430000
17
b11000110 0
b11000110 C
0+
#1435000
1"
b11000110 (
b11000110 H
b101 K
1+
#1440000
07
0+
#1445000
1+
#1450000
17
b10101110 0
b10101110 C
0+
#1455000
b110 K
1+
#1460000
07
0+
#1465000
1+
#1470000
17
b10111100 0
b10111100 C
0+
#1475000
b111 K
1+
#1480000
07
0+
#1485000
1+
#1490000
17
b101010 0
b101010 C
0+
#1495000
0%
b0 K
1+
#1500000
07
0+
#1505000
1+
#1510000
b11111111 0
b11111111 C
17
0+
#1515000
1+
#1520000
b101 .
07
0+
#1525000
1+
#1530000
13
0+
#1535000
1%
b101 J
b10101110 (
b10101110 H
b101 I
1+
#1540000
b110 .
03
0+
#1545000
1+
#1550000
13
0+
#1555000
b110 J
b10111100 (
b10111100 H
b110 I
1+
#1560000
b111 .
03
0+
#1565000
1+
#1570000
13
0+
#1575000
b111 J
b101010 (
b101010 H
b111 I
1+
#1580000
b1000 .
03
0+
#1585000
1+
#1590000
13
0+
#1595000
0"
b0 J
b11000110 (
b11000110 H
b0 I
1+
#1600000
03
0+
#1605000
1+
#1610000
14
0+
#1615000
1+
#1620000
04
0+
